cfx_address/__init__.py
cfx_address/_utils.py
cfx_address/address.py
cfx_address/base32.py
cfx_address/consts.py
cfx_address/py.typed
cfx_address/types.py
cfx_address/utils.py
cfx_address-1.2.4.dist-info/METADATA
cfx_address-1.2.4.dist-info/WHEEL
cfx_address-1.2.4.dist-info/top_level.txt
cfx_address-1.2.4.dist-info/RECORD
