Metadata-Version: 2.1
Name: cfx-address
Version: 1.2.4
Author: The Conflux foundation
Author-email: wenda.zhang@confluxnetwork.org
Keywords: Conflux,base32,address
Classifier: Development Status :: 3 - Alpha
Classifier: Intended Audience :: Education
Classifier: Programming Language :: Python :: 2
Classifier: Programming Language :: Python :: 3
Classifier: Operating System :: MacOS :: MacOS X
Classifier: Operating System :: Microsoft :: Windows
Requires-Python: >=3.7
Requires-Dist: eth-utils>=1.9.5
Requires-Dist: hexbytes
Requires-Dist: cfx-utils>=1.0.2
Requires-Dist: typing-extensions
Requires-Dist: pydantic<3,>=2.0.0
Requires-Dist: cached-property==1.5.2; python_version < "3.8"
Provides-Extra: dev
Requires-Dist: pytest<9,>=8; extra == "dev"
Requires-Dist: sphinx<8; extra == "dev"
Requires-Dist: sphinx-rtd-theme<3,>=2.0.0; extra == "dev"
Requires-Dist: wheel; extra == "dev"
Requires-Dist: pycryptodome; extra == "dev"
Requires-Dist: bumpversion==0.6.0; extra == "dev"
Provides-Extra: docs
Requires-Dist: sphinx<8; extra == "docs"
Requires-Dist: sphinx-rtd-theme<3,>=2.0.0; extra == "docs"
Provides-Extra: linter
Provides-Extra: tester
Requires-Dist: pytest<9,>=8; extra == "tester"
